antlr4_tool_runner.py
antlr4_tools_ken_domino-0.3.dist-info/licenses/LICENSE
antlr4_tools_ken_domino-0.3.dist-info/METADATA
antlr4_tools_ken_domino-0.3.dist-info/WHEEL
antlr4_tools_ken_domino-0.3.dist-info/entry_points.txt
antlr4_tools_ken_domino-0.3.dist-info/top_level.txt
antlr4_tools_ken_domino-0.3.dist-info/RECORD
