Metadata-Version: 2.4
Name: antlr4-tools-ken.domino
Version: 0.3
Summary: Tools to run ANTLR4 tool and grammar interpreter/profiler
Home-page: http://www.antlr.org
Author: Ken Domino
Author-email: ken.domino@gmail.com
License: MIT
Classifier: License :: OSI Approved :: MIT License
Classifier: Intended Audience :: Developers
License-File: LICENSE
Requires-Dist: install-jdk
Dynamic: author
Dynamic: author-email
Dynamic: classifier
Dynamic: home-page
Dynamic: license
Dynamic: license-file
Dynamic: requires-dist
Dynamic: summary
